{
  "enabled": true,
  "indexed_chunks": 94,
  "matches": [
    {
      "id": "pubmed:27574741:2",
      "score": 0.6861160397529602,
      "metadata": {
        "id": "pubmed:27574741:2",
        "doc_id": "27574741",
        "source": "pubmed",
        "title": "Lung cancer: current therapies and new targeted treatments.",
        "study_type": "Journal Article, Review",
        "year": "2017",
        "url": "https://pubmed.ncbi.nlm.nih.gov/27574741/",
        "text": "We discuss prevention and early detection of lung cancer with an emphasis on lung cancer screening."
      }
    },
    {
      "id": "clinicaltrials:NCT02916745:0",
      "score": 0.6776835322380066,
      "metadata": {
        "id": "clinicaltrials:NCT02916745:0",
        "doc_id": "NCT02916745",
        "source": "clinicaltrials",
        "title": "Feasibility Study of Using Navigational Bronchoscopy to Perform PDT-Photofrin® in Unresectable Peripheral Lung Cancer",
        "study_type": "INTERVENTIONAL",
        "year": "2020",
        "url": "https://clinicaltrials.gov/study/NCT02916745",
        "text": "Lung cancer accounts for almost one-third of cancer deaths."
      }
    },
    {
      "id": "pubmed:30572031:0",
      "score": 0.6726204752922058,
      "metadata": {
        "id": "pubmed:30572031:0",
        "doc_id": "30572031",
        "source": "pubmed",
        "title": "Best Practices Recommendations for Diagnostic Immunohistochemistry in Lung Cancer.",
        "study_type": "Journal Article, Research Support, Non-U.S. Gov't",
        "year": "2019",
        "url": "https://pubmed.ncbi.nlm.nih.gov/30572031/",
        "text": "After discussions in several International Association for the Study of Lung Cancer Pathology Committee meetings, the issues and caveats were summarized in terms of 11 key questions covering common and important diagnostic situations in a daily clinical practice with some relevant challenging queries."
      }
    },
    {
      "id": "pubmed:33972746:1",
      "score": 0.6709849834442139,
      "metadata": {
        "id": "pubmed:33972746:1",
        "doc_id": "33972746",
        "source": "pubmed",
        "title": "COVID-19 and the multidisciplinary care of patients with lung cancer: an evidence-based review and commentary.",
        "study_type": "Journal Article, Research Support, Non-U.S. Gov't, Review",
        "year": "2021",
        "url": "https://pubmed.ncbi.nlm.nih.gov/33972746/",
        "text": "Review of current evidence and commentary included awareness and help-seeking; lung cancer screening; primary care assessment and referral; diagnosis and treatment in secondary care, including oncology and surgery; patient experience and palliative care."
      }
    },
    {
      "id": "pubmed:39118957:1",
      "score": 0.6483585834503174,
      "metadata": {
        "id": "pubmed:39118957:1",
        "doc_id": "39118957",
        "source": "pubmed",
        "title": "Review on endobronchial therapies-current status and future.",
        "study_type": "Journal Article, Review",
        "year": "2024",
        "url": "https://pubmed.ncbi.nlm.nih.gov/39118957/",
        "text": "Lung cancer screening has led to the discovery of more pre-malignant or early-stage lung cancers, and the focus has shifted from treatment to prevention."
      }
    },
    {
      "id": "pubmed:35369606:1",
      "score": 0.6465158462524414,
      "metadata": {
        "id": "pubmed:35369606:1",
        "doc_id": "35369606",
        "source": "pubmed",
        "title": "Trends of Molecular Testing for Lung Cancer at the King Faisal Hospital, Kigali: Therapeutic and Survival Implications.",
        "study_type": "Journal Article",
        "year": "2022",
        "url": "https://pubmed.ncbi.nlm.nih.gov/35369606/",
        "text": "This study describes the experience in lung cancer diagnosis, molecular and biomarker testing, and treatment for advanced cases in a single institution in East Africa, between the years 2019 and 2021."
      }
    },
    {
      "id": "clinicaltrials:NCT03576937:1",
      "score": 0.6338520050048828,
      "metadata": {
        "id": "clinicaltrials:NCT03576937:1",
        "doc_id": "NCT03576937",
        "source": "clinicaltrials",
        "title": "Achieving Value in Cancer Diagnostics: Blood Versus Tissue Molecular Profiling - a Prospective Canadian Study",
        "study_type": "OBSERVATIONAL",
        "year": "2023",
        "url": "https://clinicaltrials.gov/study/NCT03576937",
        "text": "However, obtaining sufficient tumour tissue to test for these molecular alterations, as well as those with emerging targeted therapies, is challenging in lung cancer."
      }
    },
    {
      "id": "pubmed:29355391:0",
      "score": 0.6326690912246704,
      "metadata": {
        "id": "pubmed:29355391:0",
        "doc_id": "29355391",
        "source": "pubmed",
        "title": "Updated Molecular Testing Guideline for the Selection of Lung Cancer Patients for Treatment With Targeted Tyrosine Kinase Inhibitors: Guideline From the College of American Pathologists, the International Association for the Study of Lung Cancer, and the Association for Molecular Pathology.",
        "study_type": "Journal Article, Practice Guideline",
        "year": "2018",
        "url": "https://pubmed.ncbi.nlm.nih.gov/29355391/",
        "text": "- The College of American Pathologists, the International Association for the Study of Lung Cancer, and the Association for Molecular Pathology convened an expert panel to develop an evidence-based guideline to help define the key questions and literature search terms, review abstracts and full articles, and draft recommendations."
      }
    },
    {
      "id": "pubmed:30211037:1",
      "score": 0.6316414475440979,
      "metadata": {
        "id": "pubmed:30211037:1",
        "doc_id": "30211037",
        "source": "pubmed",
        "title": "The 8",
        "study_type": "Journal Article, Review",
        "year": "2018",
        "url": "https://pubmed.ncbi.nlm.nih.gov/30211037/",
        "text": "Guidelines are constantly being reviewed as more data becomes available to provide the most accurate prognostic markers, hence aiding in the clinical detection and staging of lung cancer."
      }
    },
    {
      "id": "pubmed:29700105:0",
      "score": 0.6301765441894531,
      "metadata": {
        "id": "pubmed:29700105:0",
        "doc_id": "29700105",
        "source": "pubmed",
        "title": "Lung cancer staging: a concise update.",
        "study_type": "Journal Article, Review",
        "year": "2018",
        "url": "https://pubmed.ncbi.nlm.nih.gov/29700105/",
        "text": "Diagnosis and clinical staging of lung cancer are fundamental to planning therapy."
      }
    },
    {
      "id": "pubmed:41307293:1",
      "score": 0.627196729183197,
      "metadata": {
        "id": "pubmed:41307293:1",
        "doc_id": "41307293",
        "source": "pubmed",
        "title": "Long-term hormone therapy for perimenopausal and postmenopausal women.",
        "study_type": "Journal Article, Systematic Review",
        "year": "2025",
        "url": "https://pubmed.ncbi.nlm.nih.gov/41307293/",
        "text": "It may make little to no difference to the risk of lung cancer (RR 1.04, 95% CI 0.73 to 1.48; low-certainty evidence)."
      }
    },
    {
      "id": "pubmed:38641511:2",
      "score": 0.6263546347618103,
      "metadata": {
        "id": "pubmed:38641511:2",
        "doc_id": "38641511",
        "source": "pubmed",
        "title": "Development of new techniques and clinical applications of liquid biopsy in lung cancer management.",
        "study_type": "Journal Article, Review, Research Support, Non-U.S. Gov't",
        "year": "2024",
        "url": "https://pubmed.ncbi.nlm.nih.gov/38641511/",
        "text": "Lung cancer is an exceedingly malignant tumor reported as having the highest morbidity and mortality of any cancer worldwide, thus posing a great threat to global health."
      }
    },
    {
      "id": "pubmed:34753715:1",
      "score": 0.6263513565063477,
      "metadata": {
        "id": "pubmed:34753715:1",
        "doc_id": "34753715",
        "source": "pubmed",
        "title": "Advances in systemic therapy for non-small cell lung cancer.",
        "study_type": "Journal Article, Review",
        "year": "2021",
        "url": "https://pubmed.ncbi.nlm.nih.gov/34753715/",
        "text": "Lung cancer remains a leading cause of cancer related mortality worldwide."
      }
    },
    {
      "id": "openalex:https://openalex.org/W2106787323:1",
      "score": 0.6259598135948181,
      "metadata": {
        "id": "openalex:https://openalex.org/W2106787323:1",
        "doc_id": "https://openalex.org/W2106787323",
        "source": "openalex",
        "title": "Global cancer statistics",
        "study_type": "article",
        "year": "2011",
        "url": "https://doi.org/10.3322/caac.20107",
        "text": "Lung cancer is the leading cancer site in males, comprising 17% of the total new cancer cases and 23% of the total cancer deaths."
      }
    },
    {
      "id": "pubmed:24067269:2",
      "score": 0.62464439868927,
      "metadata": {
        "id": "pubmed:24067269:2",
        "doc_id": "24067269",
        "source": "pubmed",
        "title": "Lung cancer: needs assessment, treatment and therapies.",
        "study_type": "Journal Article, Review",
        "year": "2013",
        "url": "https://pubmed.ncbi.nlm.nih.gov/24067269/",
        "text": "It is not within the scope of this article to discuss each type and aspect of lung cancer in detail and further reading is encouraged."
      }
    },
    {
      "id": "pubmed:35369606:2",
      "score": 0.6245194673538208,
      "metadata": {
        "id": "pubmed:35369606:2",
        "doc_id": "35369606",
        "source": "pubmed",
        "title": "Trends of Molecular Testing for Lung Cancer at the King Faisal Hospital, Kigali: Therapeutic and Survival Implications.",
        "study_type": "Journal Article",
        "year": "2022",
        "url": "https://pubmed.ncbi.nlm.nih.gov/35369606/",
        "text": "This was a retrospective observational study evaluating patients with metastatic (stage IV) lung cancer."
      }
    },
    {
      "id": "pubmed:34847189:2",
      "score": 0.622816801071167,
      "metadata": {
        "id": "pubmed:34847189:2",
        "doc_id": "34847189",
        "source": "pubmed",
        "title": "Countering the advert effects of lung cancer on the anticancer potential of dendritic cell populations reinstates sensitivity to anti-PD-1 therapy.",
        "study_type": "Journal Article, Research Support, Non-U.S. Gov't",
        "year": "2021",
        "url": "https://pubmed.ncbi.nlm.nih.gov/34847189/",
        "text": "Lung cancer is the leading cause of cancer-related deaths."
      }
    },
    {
      "id": "pubmed:40480014:2",
      "score": 0.6220012903213501,
      "metadata": {
        "id": "pubmed:40480014:2",
        "doc_id": "40480014",
        "source": "pubmed",
        "title": "AGREE-II appraisal of lung cancer management clinical practice guidelines by the OPTIMA consortium.",
        "study_type": "Journal Article",
        "year": "2025",
        "url": "https://pubmed.ncbi.nlm.nih.gov/40480014/",
        "text": "We identified and critically appraised 21 European lung cancer guidelines published between 2009 and 2025."
      }
    },
    {
      "id": "pubmed:35323350:1",
      "score": 0.6165987253189087,
      "metadata": {
        "id": "pubmed:35323350:1",
        "doc_id": "35323350",
        "source": "pubmed",
        "title": "Non-Small-Cell Lung Cancer in 2022: A Review for General Practitioners in Oncology.",
        "study_type": "Journal Article, Review",
        "year": "2022",
        "url": "https://pubmed.ncbi.nlm.nih.gov/35323350/",
        "text": "The focus of this review is to highlight recent data in screening for lung cancer, management of patients with early and locally-advanced non-small cell lung cancer, as well as management of patients with metastatic disease."
      }
    },
    {
      "id": "clinicaltrials:NCT04035486:1",
      "score": 0.6159894466400146,
      "metadata": {
        "id": "clinicaltrials:NCT04035486:1",
        "doc_id": "NCT04035486",
        "source": "clinicaltrials",
        "title": "A Study of Osimertinib With or Without Chemotherapy as 1st Line Treatment in Patients With Mutated Epidermal Growth Factor Receptor Non-Small Cell Lung Cancer (FLAURA2)",
        "study_type": "INTERVENTIONAL",
        "year": "2025",
        "url": "https://clinicaltrials.gov/study/NCT04035486",
        "text": "Some lung cancers are due to mutations in the Deoxyribonucleic acid (DNA) which, if known, can help physicians decide the best treatment for their patients."
      }
    },
    {
      "id": "pubmed:15110450:1",
      "score": 0.6140954494476318,
      "metadata": {
        "id": "pubmed:15110450:1",
        "doc_id": "15110450",
        "source": "pubmed",
        "title": "Radiation treatment of lung cancer--patterns of practice in Canada.",
        "study_type": "Comparative Study, Journal Article, Research Support, Non-U.S. Gov't",
        "year": "2004",
        "url": "https://pubmed.ncbi.nlm.nih.gov/15110450/",
        "text": "Canadian practice in the treatment of lung cancers shows some variations although it is consistent with the trends in the literature."
      }
    },
    {
      "id": "pubmed:40133478:1",
      "score": 0.6130865216255188,
      "metadata": {
        "id": "pubmed:40133478:1",
        "doc_id": "40133478",
        "source": "pubmed",
        "title": "Update 2025: Management of Non‑Small-Cell Lung Cancer.",
        "study_type": "Journal Article, Review",
        "year": "2025",
        "url": "https://pubmed.ncbi.nlm.nih.gov/40133478/",
        "text": "Lung cancer remains the leading cause of cancer-related mortality worldwide."
      }
    },
    {
      "id": "pubmed:40871018:1",
      "score": 0.6128694415092468,
      "metadata": {
        "id": "pubmed:40871018:1",
        "doc_id": "40871018",
        "source": "pubmed",
        "title": "Inhalable Nanomaterial Discoveries for Lung Cancer Therapy: A Review.",
        "study_type": "Journal Article, Review",
        "year": "2025",
        "url": "https://pubmed.ncbi.nlm.nih.gov/40871018/",
        "text": "Lung cancer remains one of the most common and deadliest forms of cancer worldwide despite notable advancements in its management."
      }
    },
    {
      "id": "pubmed:41526992:1",
      "score": 0.6127306222915649,
      "metadata": {
        "id": "pubmed:41526992:1",
        "doc_id": "41526992",
        "source": "pubmed",
        "title": "LUNG CARCINOIDS (Lung Neuroendocrine Tumors).",
        "study_type": "Journal Article",
        "year": "2026",
        "url": "https://pubmed.ncbi.nlm.nih.gov/41526992/",
        "text": "This narrative review written by experts aims to provide a comprehensive synthesis of current knowledge and guidelines on lung carcinoids, emphasizing the multidimensional approach required for effective diagnosis and management."
      }
    },
    {
      "id": "pubmed:33175991:1",
      "score": 0.612597644329071,
      "metadata": {
        "id": "pubmed:33175991:1",
        "doc_id": "33175991",
        "source": "pubmed",
        "title": "Update 2020: Management of Non-Small Cell Lung Cancer.",
        "study_type": "Journal Article, Review",
        "year": "2020",
        "url": "https://pubmed.ncbi.nlm.nih.gov/33175991/",
        "text": "This review will address updates in lung cancer screening, liquid biopsy, and immunotherapy in the front-line setting."
      }
    },
    {
      "id": "pubmed:39337530:1",
      "score": 0.6121392250061035,
      "metadata": {
        "id": "pubmed:39337530:1",
        "doc_id": "39337530",
        "source": "pubmed",
        "title": "Emerging Targets in Non-Small Cell Lung Cancer.",
        "study_type": "Journal Article, Review",
        "year": "2024",
        "url": "https://pubmed.ncbi.nlm.nih.gov/39337530/",
        "text": "Lung cancer is responsible for a high burden of disease globally."
      }
    },
    {
      "id": "pubmed:41024606:0",
      "score": 0.6097329258918762,
      "metadata": {
        "id": "pubmed:41024606:0",
        "doc_id": "41024606",
        "source": "pubmed",
        "title": "American Association for Bronchology and Interventional Pulmonology (AABIP) Evidence-Based Guidelines on Bronchoscopic Diagnosis and Staging of Lung Cancer.",
        "study_type": "Journal Article, Practice Guideline",
        "year": "2025",
        "url": "https://pubmed.ncbi.nlm.nih.gov/41024606/",
        "text": "Lung cancer remains a predominant cause of cancer-related deaths worldwide, and there are notable geographic and institutional differences in both diagnostic and staging approaches."
      }
    },
    {
      "id": "pubmed:29352525:0",
      "score": 0.6045322418212891,
      "metadata": {
        "id": "pubmed:29352525:0",
        "doc_id": "29352525",
        "source": "pubmed",
        "title": "An MRM-Based Cytokeratin Marker Assay as a Tool for Cancer Studies: Application to Lung Cancer Pleural Effusions.",
        "study_type": "Journal Article, Research Support, Non-U.S. Gov't",
        "year": "2018",
        "url": "https://pubmed.ncbi.nlm.nih.gov/29352525/",
        "text": "An MRM-based CK assay for carcinoma studies can differentiate between the three lung cancer histological types using less-invasive PE sampling providing potential therapy-guiding information on patients that are inoperable."
      }
    },
    {
      "id": "pubmed:36290875:0",
      "score": 0.6028514504432678,
      "metadata": {
        "id": "pubmed:36290875:0",
        "doc_id": "36290875",
        "source": "pubmed",
        "title": "Access to Cancer Drugs in Canada.",
        "study_type": "Editorial",
        "year": "2022",
        "url": "https://pubmed.ncbi.nlm.nih.gov/36290875/",
        "text": "Lung cancer, because of the multiple subtypes now identifiable and because of the myriad of new and effective therapies, provides fertile ground to highlight issues related to oncology drug access in Canada [...]."
      }
    },
    {
      "id": "pubmed:19445746:1",
      "score": 0.6016722321510315,
      "metadata": {
        "id": "pubmed:19445746:1",
        "doc_id": "19445746",
        "source": "pubmed",
        "title": "Lung cancer.",
        "study_type": "Journal Article, Systematic Review",
        "year": "2009",
        "url": "https://pubmed.ncbi.nlm.nih.gov/19445746/",
        "text": "What are the effects of treatments for small cell lung cancer?"
      }
    },
    {
      "id": "pubmed:21406127:1",
      "score": 0.6016722321510315,
      "metadata": {
        "id": "pubmed:21406127:1",
        "doc_id": "21406127",
        "source": "pubmed",
        "title": "Lung cancer.",
        "study_type": "Journal Article, Systematic Review",
        "year": "2010",
        "url": "https://pubmed.ncbi.nlm.nih.gov/21406127/",
        "text": "What are the effects of treatments for small cell lung cancer?"
      }
    },
    {
      "id": "pubmed:26620497:0",
      "score": 0.5986562967300415,
      "metadata": {
        "id": "pubmed:26620497:0",
        "doc_id": "26620497",
        "source": "pubmed",
        "title": "Management of advanced non-small cell lung cancers with known mutations or rearrangements: latest evidence and treatment approaches.",
        "study_type": "Journal Article, Research Support, N.I.H., Extramural, Research Support, Non-U.S. Gov't, Review",
        "year": "2016",
        "url": "https://pubmed.ncbi.nlm.nih.gov/26620497/",
        "text": "Precision oncology is now the evidence-based standard of care for the management of many advanced non-small cell lung cancers (NSCLCs)."
      }
    },
    {
      "id": "pubmed:24067269:1",
      "score": 0.5965907573699951,
      "metadata": {
        "id": "pubmed:24067269:1",
        "doc_id": "24067269",
        "source": "pubmed",
        "title": "Lung cancer: needs assessment, treatment and therapies.",
        "study_type": "Journal Article, Review",
        "year": "2013",
        "url": "https://pubmed.ncbi.nlm.nih.gov/24067269/",
        "text": "The latest figures for the UK show that there are approximately 39000 cases each year and that lung cancer accounts for about 22% of all cancer deaths (Cancer Research UK, 2013a)."
      }
    },
    {
      "id": "pubmed:29355391:1",
      "score": 0.5960148572921753,
      "metadata": {
        "id": "pubmed:29355391:1",
        "doc_id": "29355391",
        "source": "pubmed",
        "title": "Updated Molecular Testing Guideline for the Selection of Lung Cancer Patients for Treatment With Targeted Tyrosine Kinase Inhibitors: Guideline From the College of American Pathologists, the International Association for the Study of Lung Cancer, and the Association for Molecular Pathology.",
        "study_type": "Journal Article, Practice Guideline",
        "year": "2018",
        "url": "https://pubmed.ncbi.nlm.nih.gov/29355391/",
        "text": "- In 2013, an evidence-based guideline was published by the College of American Pathologists, the International Association for the Study of Lung Cancer, and the Association for Molecular Pathology to set standards for the molecular analysis of lung cancers to guide treatment decisions with targeted inhibitors."
      }
    },
    {
      "id": "pubmed:38031889:0",
      "score": 0.5945765972137451,
      "metadata": {
        "id": "pubmed:38031889:0",
        "doc_id": "38031889",
        "source": "pubmed",
        "title": "What's new in thoracic oncology.",
        "study_type": "Journal Article, Review",
        "year": "2024",
        "url": "https://pubmed.ncbi.nlm.nih.gov/38031889/",
        "text": "In this review, we will discuss new diagnostic techniques for lung cancer, innovations in surgery, and major updates on latest treatment options including immunotherapy."
      }
    },
    {
      "id": "pubmed:35732383:1",
      "score": 0.5933829545974731,
      "metadata": {
        "id": "pubmed:35732383:1",
        "doc_id": "35732383",
        "source": "pubmed",
        "title": "Personalised Lung Cancer Screening (PLuS) study to assess the importance of coexisting chronic conditions to clinical practice and policy: protocol for a multicentre observational study.",
        "study_type": "Journal Article, Research Support, Non-U.S. Gov't, Research Support, N.I.H., Extramural",
        "year": "2022",
        "url": "https://pubmed.ncbi.nlm.nih.gov/35732383/",
        "text": "The Personalised Lung Cancer Screening (PLuS) study will help close this knowledge gap by leveraging real-world data to fully characterise LCS recipients."
      }
    },
    {
      "id": "pubmed:39236577:1",
      "score": 0.5902523398399353,
      "metadata": {
        "id": "pubmed:39236577:1",
        "doc_id": "39236577",
        "source": "pubmed",
        "title": "New diagnostic and nonsurgical local treatment modalities for early stage lung cancer.",
        "study_type": "Journal Article, Review",
        "year": "2024",
        "url": "https://pubmed.ncbi.nlm.nih.gov/39236577/",
        "text": "This paper highlights developments in diagnostic and nonsurgical local treatment modalities that have changed the management of early-stage lung cancer."
      }
    },
    {
      "id": "pubmed:38878052:0",
      "score": 0.5892987847328186,
      "metadata": {
        "id": "pubmed:38878052:0",
        "doc_id": "38878052",
        "source": "pubmed",
        "title": "The 2023 American Association for Thoracic Surgery (AATS) Expert Consensus Document: Management of subsolid lung nodules.",
        "study_type": "Journal Article, Practice Guideline, Review, Consensus Statement",
        "year": "2024",
        "url": "https://pubmed.ncbi.nlm.nih.gov/38878052/",
        "text": "Lung cancers that present as radiographic subsolid nodules represent a subtype with distinct biological behavior and outcomes."
      }
    },
    {
      "id": "clinicaltrials:NCT01351116:1",
      "score": 0.5888932943344116,
      "metadata": {
        "id": "clinicaltrials:NCT01351116:1",
        "doc_id": "NCT01351116",
        "source": "clinicaltrials",
        "title": "A Trial to Evaluate the Improvement in Lung Cancer Patients Receiving Radiation With or Without Brachytherapy",
        "study_type": "INTERVENTIONAL",
        "year": "2017",
        "url": "https://clinicaltrials.gov/study/NCT01351116",
        "text": "Benefit will be assessed by measuring the proportion of patients who achieve symptomatic improvement in lung cancer symptoms."
      }
    },
    {
      "id": "pubmed:35369606:0",
      "score": 0.5888370275497437,
      "metadata": {
        "id": "pubmed:35369606:0",
        "doc_id": "35369606",
        "source": "pubmed",
        "title": "Trends of Molecular Testing for Lung Cancer at the King Faisal Hospital, Kigali: Therapeutic and Survival Implications.",
        "study_type": "Journal Article",
        "year": "2022",
        "url": "https://pubmed.ncbi.nlm.nih.gov/35369606/",
        "text": "Little is known on the data around lung cancer and its treatment outcomes in Sub-Saharan Africa."
      }
    },
    {
      "id": "pubmed:33972746:2",
      "score": 0.5874899625778198,
      "metadata": {
        "id": "pubmed:33972746:2",
        "doc_id": "33972746",
        "source": "pubmed",
        "title": "COVID-19 and the multidisciplinary care of patients with lung cancer: an evidence-based review and commentary.",
        "study_type": "Journal Article, Research Support, Non-U.S. Gov't, Review",
        "year": "2021",
        "url": "https://pubmed.ncbi.nlm.nih.gov/33972746/",
        "text": "We searched for COVID-19 and lung cancer publications and brought together a multidisciplinary group of stakeholders to review and comment on the evidence and challenges."
      }
    },
    {
      "id": "pubmed:35323350:2",
      "score": 0.5866687297821045,
      "metadata": {
        "id": "pubmed:35323350:2",
        "doc_id": "35323350",
        "source": "pubmed",
        "title": "Non-Small-Cell Lung Cancer in 2022: A Review for General Practitioners in Oncology.",
        "study_type": "Journal Article, Review",
        "year": "2022",
        "url": "https://pubmed.ncbi.nlm.nih.gov/35323350/",
        "text": "Lung cancer is the leading cause of cancer death in Canada and a significant cause of morbidity for patients and their loved ones."
      }
    },
    {
      "id": "pubmed:34862216:0",
      "score": 0.5862986445426941,
      "metadata": {
        "id": "pubmed:34862216:0",
        "doc_id": "34862216",
        "source": "pubmed",
        "title": "Lung cancer for the non-respiratory physician.",
        "study_type": "Journal Article, Review",
        "year": "2021",
        "url": "https://pubmed.ncbi.nlm.nih.gov/34862216/",
        "text": "We provide an overview of the core lung cancer diagnostic steps, recognition and management of acute presentations as well as the latest treatment options."
      }
    },
    {
      "id": "pubmed:17620772:1",
      "score": 0.583954930305481,
      "metadata": {
        "id": "pubmed:17620772:1",
        "doc_id": "17620772",
        "source": "pubmed",
        "title": "Lung cancer adjuvant therapy.",
        "study_type": "Journal Article, Review",
        "year": "2007",
        "url": "https://pubmed.ncbi.nlm.nih.gov/17620772/",
        "text": "Lung cancer is the most common cause of cancer-related mortality in North America with non-small cell lung cancer representing the majority of cases."
      }
    },
    {
      "id": "pubmed:38417091:0",
      "score": 0.5808396339416504,
      "metadata": {
        "id": "pubmed:38417091:0",
        "doc_id": "38417091",
        "source": "pubmed",
        "title": "Therapy for Stage IV Non-Small Cell Lung Cancer With Driver Alterations: ASCO Living Guideline, Version 2023.3.",
        "study_type": "Journal Article, Practice Guideline, Systematic Review",
        "year": "2024",
        "url": "https://pubmed.ncbi.nlm.nih.gov/38417091/",
        "text": "To provide evidence-based recommendations for patients with stage IV non-small cell lung cancer with driver alterations."
      }
    },
    {
      "id": "pubmed:41632926:0",
      "score": 0.5808396339416504,
      "metadata": {
        "id": "pubmed:41632926:0",
        "doc_id": "41632926",
        "source": "pubmed",
        "title": "Therapy for Stage IV Non-Small Cell Lung Cancer With Driver Alterations: ASCO Living Guideline, 2026.3.0.",
        "study_type": "Letter",
        "year": "2026",
        "url": "https://pubmed.ncbi.nlm.nih.gov/41632926/",
        "text": "To provide evidence-based recommendations for patients with stage IV non-small cell lung cancer with driver alterations."
      }
    },
    {
      "id": "pubmed:38641511:0",
      "score": 0.579568088054657,
      "metadata": {
        "id": "pubmed:38641511:0",
        "doc_id": "38641511",
        "source": "pubmed",
        "title": "Development of new techniques and clinical applications of liquid biopsy in lung cancer management.",
        "study_type": "Journal Article, Review, Research Support, Non-U.S. Gov't",
        "year": "2024",
        "url": "https://pubmed.ncbi.nlm.nih.gov/38641511/",
        "text": "Additionally, it will summarize the latest applications of liquid biopsy for the early detection, diagnosis, treatment, and prognosis of lung cancer."
      }
    },
    {
      "id": "pubmed:27343441:1",
      "score": 0.5793554186820984,
      "metadata": {
        "id": "pubmed:27343441:1",
        "doc_id": "27343441",
        "source": "pubmed",
        "title": "Comprehensive Clinical Staging for Resectable Lung Cancer: Clinicopathological Correlations and the Role of Brain MRI.",
        "study_type": "Journal Article",
        "year": "2016",
        "url": "https://pubmed.ncbi.nlm.nih.gov/27343441/",
        "text": "Of 315 patients with primary lung cancer, 55.6% were female and the mean age was 70 ± 9.6 years."
      }
    },
    {
      "id": "pubmed:36806787:2",
      "score": 0.5786510705947876,
      "metadata": {
        "id": "pubmed:36806787:2",
        "doc_id": "36806787",
        "source": "pubmed",
        "title": "Rare molecular subtypes of lung cancer.",
        "study_type": "Journal Article, Review, Research Support, N.I.H., Extramural, Research Support, Non-U.S. Gov't",
        "year": "2023",
        "url": "https://pubmed.ncbi.nlm.nih.gov/36806787/",
        "text": "Oncogenes that occur in ≤5% of non-small-cell lung cancers have been defined as 'rare'; nonetheless, this frequency can correspond to a substantial number of patients diagnosed annually."
      }
    },
    {
      "id": "pubmed:19445746:2",
      "score": 0.5752708911895752,
      "metadata": {
        "id": "pubmed:19445746:2",
        "doc_id": "19445746",
        "source": "pubmed",
        "title": "Lung cancer.",
        "study_type": "Journal Article, Systematic Review",
        "year": "2009",
        "url": "https://pubmed.ncbi.nlm.nih.gov/19445746/",
        "text": "Lung cancer is the leading cause of cancer deaths in both men and women, with 80-90% of cases caused by smoking."
      }
    },
    {
      "id": "pubmed:26297204:2",
      "score": 0.5749998092651367,
      "metadata": {
        "id": "pubmed:26297204:2",
        "doc_id": "26297204",
        "source": "pubmed",
        "title": "Lung cancer: Biology and treatment options.",
        "study_type": "Journal Article, Research Support, N.I.H., Extramural, Research Support, Non-U.S. Gov't, Review",
        "year": "2015",
        "url": "https://pubmed.ncbi.nlm.nih.gov/26297204/",
        "text": "Despite the improvements in diagnosis and therapy made during the past 25 years, the prognosis for patients with lung cancer is still unsatisfactory."
      }
    },
    {
      "id": "pubmed:41877745:1",
      "score": 0.5696343779563904,
      "metadata": {
        "id": "pubmed:41877745:1",
        "doc_id": "41877745",
        "source": "pubmed",
        "title": "The global cancer crisis: a review of growing burden, deepening inequality and initiatives for prevention and early detection.",
        "study_type": "Journal Article, Review",
        "year": "2026",
        "url": "https://pubmed.ncbi.nlm.nih.gov/41877745/",
        "text": "Lung cancer leads the global toll, representing 12% of all cases but 19% of deaths, followed by breast cancer (12% of cases) and colorectal cancer (9.6%)."
      }
    },
    {
      "id": "pubmed:21406127:2",
      "score": 0.5692081451416016,
      "metadata": {
        "id": "pubmed:21406127:2",
        "doc_id": "21406127",
        "source": "pubmed",
        "title": "Lung cancer.",
        "study_type": "Journal Article, Systematic Review",
        "year": "2010",
        "url": "https://pubmed.ncbi.nlm.nih.gov/21406127/",
        "text": "Lung cancer is the leading cause of cancer deaths in both men and women, with 80% to 90% of cases caused by smoking."
      }
    },
    {
      "id": "pubmed:41632927:0",
      "score": 0.5691902041435242,
      "metadata": {
        "id": "pubmed:41632927:0",
        "doc_id": "41632927",
        "source": "pubmed",
        "title": "Therapy for Stage IV Non-Small Cell Lung Cancer Without Driver Alterations: ASCO Living Guideline, 2026.3.0.",
        "study_type": "Journal Article",
        "year": "2026",
        "url": "https://pubmed.ncbi.nlm.nih.gov/41632927/",
        "text": "To provide evidence-based recommendations for patients with stage IV non-small cell lung cancer (NSCLC) without driver alterations."
      }
    },
    {
      "id": "pubmed:38417098:0",
      "score": 0.5691902041435242,
      "metadata": {
        "id": "pubmed:38417098:0",
        "doc_id": "38417098",
        "source": "pubmed",
        "title": "Therapy for Stage IV Non-Small Cell Lung Cancer Without Driver Alterations: ASCO Living Guideline, Version 2023.3.",
        "study_type": "Journal Article, Practice Guideline, Systematic Review",
        "year": "2024",
        "url": "https://pubmed.ncbi.nlm.nih.gov/38417098/",
        "text": "To provide evidence-based recommendations for patients with stage IV non-small cell lung cancer (NSCLC) without driver alterations."
      }
    },
    {
      "id": "pubmed:36806787:1",
      "score": 0.5685391426086426,
      "metadata": {
        "id": "pubmed:36806787:1",
        "doc_id": "36806787",
        "source": "pubmed",
        "title": "Rare molecular subtypes of lung cancer.",
        "study_type": "Journal Article, Review, Research Support, N.I.H., Extramural, Research Support, Non-U.S. Gov't",
        "year": "2023",
        "url": "https://pubmed.ncbi.nlm.nih.gov/36806787/",
        "text": "Over the past 5 years, a surge in the identification of rare-oncogene-driven lung cancers has challenged the boundaries of traditional clinical grade diagnostic assays and profiling algorithms."
      }
    },
    {
      "id": "clinicaltrials:NCT04048954:2",
      "score": 0.5683777332305908,
      "metadata": {
        "id": "clinicaltrials:NCT04048954:2",
        "doc_id": "NCT04048954",
        "source": "clinicaltrials",
        "title": "Use of a Smartphone Application on the Detection of Complications Related to Smoking",
        "study_type": "OBSERVATIONAL",
        "year": "2020",
        "url": "https://clinicaltrials.gov/study/NCT04048954",
        "text": "An English study showed an increase in the number of operable stage cancers of 3% among smokers by calling them on a trailing cough by a simple poster campaign (\"You smoke, you cough for more than 3 weeks, consult\")."
      }
    },
    {
      "id": "pubmed:30211037:2",
      "score": 0.5675795078277588,
      "metadata": {
        "id": "pubmed:30211037:2",
        "doc_id": "30211037",
        "source": "pubmed",
        "title": "The 8",
        "study_type": "Journal Article, Review",
        "year": "2018",
        "url": "https://pubmed.ncbi.nlm.nih.gov/30211037/",
        "text": "Lung cancer is the leading cause of cancer death in both men and women."
      }
    },
    {
      "id": "pubmed:34385702:1",
      "score": 0.5674136877059937,
      "metadata": {
        "id": "pubmed:34385702:1",
        "doc_id": "34385702",
        "source": "pubmed",
        "title": "Toward personalized treatment approaches for non-small-cell lung cancer.",
        "study_type": "Journal Article, Review",
        "year": "2021",
        "url": "https://pubmed.ncbi.nlm.nih.gov/34385702/",
        "text": "Worldwide, lung cancer is the most common cause of cancer-related deaths."
      }
    },
    {
      "id": "pubmed:31049758:1",
      "score": 0.5655086040496826,
      "metadata": {
        "id": "pubmed:31049758:1",
        "doc_id": "31049758",
        "source": "pubmed",
        "title": "The Japanese Lung Cancer Society Guideline for non-small cell lung cancer, stage IV.",
        "study_type": "Journal Article, Practice Guideline",
        "year": "2019",
        "url": "https://pubmed.ncbi.nlm.nih.gov/31049758/",
        "text": "Here, we report an English version of the Japan Lung Cancer Society Guidelines 2018 for NSCLC, stages IV."
      }
    },
    {
      "id": "pubmed:40334018:1",
      "score": 0.5631258487701416,
      "metadata": {
        "id": "pubmed:40334018:1",
        "doc_id": "40334018",
        "source": "pubmed",
        "title": "Immunotherapy for resectable lung cancer.",
        "study_type": "Journal Article, Review",
        "year": "2025",
        "url": "https://pubmed.ncbi.nlm.nih.gov/40334018/",
        "text": "This comprehensive analysis amalgamates current evidence with future directions, providing a roadmap for clinicians, researchers, and stakeholders to navigate the dynamic realm of immunotherapy for surgically resectable lung cancer."
      }
    },
    {
      "id": "pubmed:36975758:2",
      "score": 0.5621503591537476,
      "metadata": {
        "id": "pubmed:36975758:2",
        "doc_id": "36975758",
        "source": "pubmed",
        "title": "Exploring state-of-the-art advances in targeted nanomedicines for managing acute and chronic inflammatory lung diseases.",
        "study_type": "Journal Article, Review",
        "year": "2022",
        "url": "https://pubmed.ncbi.nlm.nih.gov/36975758/",
        "text": "Diagnosis and treatment of lung diseases pose serious challenges."
      }
    },
    {
      "id": "clinicaltrials:NCT04863924:0",
      "score": 0.5618106126785278,
      "metadata": {
        "id": "clinicaltrials:NCT04863924:0",
        "doc_id": "NCT04863924",
        "source": "clinicaltrials",
        "title": "Accelerating Lung Cancer Diagnosis Through Liquid Biopsy",
        "study_type": "OBSERVATIONAL",
        "year": "2025",
        "url": "https://clinicaltrials.gov/study/NCT04863924",
        "text": "This study will assess the utility of liquid biopsy to accelerate the time to treatment for patients with newly diagnosed advanced non-small cell lung cancer, compared to the conventional diagnostic pathway of molecular testing of tumour tissue after imaging and biopsy."
      }
    },
    {
      "id": "pubmed:41024606:1",
      "score": 0.5599541664123535,
      "metadata": {
        "id": "pubmed:41024606:1",
        "doc_id": "41024606",
        "source": "pubmed",
        "title": "American Association for Bronchology and Interventional Pulmonology (AABIP) Evidence-Based Guidelines on Bronchoscopic Diagnosis and Staging of Lung Cancer.",
        "study_type": "Journal Article, Practice Guideline",
        "year": "2025",
        "url": "https://pubmed.ncbi.nlm.nih.gov/41024606/",
        "text": "These guidelines aim to standardize and streamline recommendations for the bronchoscopic diagnosis and staging of lung cancer."
      }
    },
    {
      "id": "pubmed:34879471:0",
      "score": 0.5597547292709351,
      "metadata": {
        "id": "pubmed:34879471:0",
        "doc_id": "34879471",
        "source": "pubmed",
        "title": "Anti PD-L1 antibody: is there a histologic-oriented efficacy? Focus on atezolizumab in squamous cell non-small cell lung cancer.",
        "study_type": "Journal Article, Review",
        "year": "2021",
        "url": "https://pubmed.ncbi.nlm.nih.gov/34879471/",
        "text": "We searched for published clinical trials in Pubmed database, using the terms \"atezolizumab\", \"squamous cell lung cancer\", \"NSCLC\" and \"non-small cell lung cancer\"."
      }
    },
    {
      "id": "pubmed:34862216:2",
      "score": 0.5582848787307739,
      "metadata": {
        "id": "pubmed:34862216:2",
        "doc_id": "34862216",
        "source": "pubmed",
        "title": "Lung cancer for the non-respiratory physician.",
        "study_type": "Journal Article, Review",
        "year": "2021",
        "url": "https://pubmed.ncbi.nlm.nih.gov/34862216/",
        "text": "The new National Optimal Lung Cancer Pathway describes 'diagnostic standards of care' in an effort to implement best practice, reduce variation and improve delays in diagnosis, staging and treatment of lung cancer."
      }
    },
    {
      "id": "pubmed:33972746:0",
      "score": 0.5580370426177979,
      "metadata": {
        "id": "pubmed:33972746:0",
        "doc_id": "33972746",
        "source": "pubmed",
        "title": "COVID-19 and the multidisciplinary care of patients with lung cancer: an evidence-based review and commentary.",
        "study_type": "Journal Article, Research Support, Non-U.S. Gov't, Review",
        "year": "2021",
        "url": "https://pubmed.ncbi.nlm.nih.gov/33972746/",
        "text": "There is a lack of published COVID-19 and lung cancer evidence-based reviews, including for the whole patient pathway."
      }
    },
    {
      "id": "openalex:https://openalex.org/W2608738563:0",
      "score": 0.5576596856117249,
      "metadata": {
        "id": "openalex:https://openalex.org/W2608738563:0",
        "doc_id": "https://openalex.org/W2608738563",
        "source": "openalex",
        "title": "Phylogenetic ctDNA analysis depicts early-stage lung cancer evolution",
        "study_type": "article",
        "year": "2017",
        "url": "https://doi.org/10.1038/nature22364",
        "text": "Phylogenetic ctDNA analysis depicts early-stage lung cancer evolution"
      }
    },
    {
      "id": "pubmed:34246791:1",
      "score": 0.55743807554245,
      "metadata": {
        "id": "pubmed:34246791:1",
        "doc_id": "34246791",
        "source": "pubmed",
        "title": "Liquid Biopsy for Advanced NSCLC: A Consensus Statement From the International Association for the Study of Lung Cancer.",
        "study_type": "Journal Article, Review, Consensus Statement",
        "year": "2021",
        "url": "https://pubmed.ncbi.nlm.nih.gov/34246791/",
        "text": "Since the publication of the first International Association for the Study of Lung Cancer (IASLC) liquid biopsy statement in 2018, several additional advances have been made in this field, leading to changes in the therapeutic decision-making algorithm for advanced NSCLC and prompting this 2021 update."
      }
    },
    {
      "id": "pubmed:29364287:0",
      "score": 0.554533839225769,
      "metadata": {
        "id": "pubmed:29364287:0",
        "doc_id": "29364287",
        "source": "pubmed",
        "title": "The biology and management of non-small cell lung cancer.",
        "study_type": "Journal Article, Research Support, Non-U.S. Gov't, Review",
        "year": "2018",
        "url": "https://pubmed.ncbi.nlm.nih.gov/29364287/",
        "text": "Important advancements in the treatment of non-small cell lung cancer (NSCLC) have been achieved over the past two decades, increasing our understanding of the disease biology and mechanisms of tumour progression, and advancing early detection and multimodal care."
      }
    },
    {
      "id": "pubmed:40334018:2",
      "score": 0.5544655919075012,
      "metadata": {
        "id": "pubmed:40334018:2",
        "doc_id": "40334018",
        "source": "pubmed",
        "title": "Immunotherapy for resectable lung cancer.",
        "study_type": "Journal Article, Review",
        "year": "2025",
        "url": "https://pubmed.ncbi.nlm.nih.gov/40334018/",
        "text": "Lung cancer remains a significant global health challenge, demanding innovative treatment strategies."
      }
    },
    {
      "id": "clinicaltrials:NCT06105021:2",
      "score": 0.5543209910392761,
      "metadata": {
        "id": "clinicaltrials:NCT06105021:2",
        "doc_id": "NCT06105021",
        "source": "clinicaltrials",
        "title": "Phase I Study of Autologous CD8+ and CD4+ Engineered T Cell Receptor T Cells in Subjects With Advanced or Metastatic Solid Tumor",
        "study_type": "INTERVENTIONAL",
        "year": "2025",
        "url": "https://clinicaltrials.gov/study/NCT06105021",
        "text": "The doctors there will regularly check the size of the cancer and the patient's health."
      }
    },
    {
      "id": "pubmed:32005431:2",
      "score": 0.5533599853515625,
      "metadata": {
        "id": "pubmed:32005431:2",
        "doc_id": "32005431",
        "source": "pubmed",
        "title": "Targeted Therapy and Checkpoint Immunotherapy in Lung Cancer.",
        "study_type": "Journal Article, Review",
        "year": "2020",
        "url": "https://pubmed.ncbi.nlm.nih.gov/32005431/",
        "text": "Comprehensive molecular characterization of lung cancer has expanded our understanding of the cellular origins and molecular pathways affected in each of these subtypes."
      }
    },
    {
      "id": "pubmed:39064229:0",
      "score": 0.5523355603218079,
      "metadata": {
        "id": "pubmed:39064229:0",
        "doc_id": "39064229",
        "source": "pubmed",
        "title": "Advances in Non-Small Cell Lung Cancer: Current Insights and Future Directions.",
        "study_type": "Journal Article, Review",
        "year": "2024",
        "url": "https://pubmed.ncbi.nlm.nih.gov/39064229/",
        "text": "The leading cause of cancer deaths worldwide is attributed to non-small cell lung cancer (NSCLC), necessitating a continual focus on improving the diagnosis and treatment of this disease."
      }
    },
    {
      "id": "pubmed:37909877:0",
      "score": 0.5518502593040466,
      "metadata": {
        "id": "pubmed:37909877:0",
        "doc_id": "37909877",
        "source": "pubmed",
        "title": "Screening for lung cancer: 2023 guideline update from the American Cancer Society.",
        "study_type": "Journal Article, Research Support, Non-U.S. Gov't, Practice Guideline",
        "year": "2024",
        "url": "https://pubmed.ncbi.nlm.nih.gov/37909877/",
        "text": "If fully implemented, these recommendations have a high likelihood of significantly reducing death and suffering from lung cancer in the United States."
      }
    },
    {
      "id": "clinicaltrials:NCT00188617:0",
      "score": 0.5495622158050537,
      "metadata": {
        "id": "clinicaltrials:NCT00188617:0",
        "doc_id": "NCT00188617",
        "source": "clinicaltrials",
        "title": "Phase 2 Study Of Neoadjuvant Iressa Treatment In Stage 1 NSCLC",
        "study_type": "INTERVENTIONAL",
        "year": "2017",
        "url": "https://clinicaltrials.gov/study/NCT00188617",
        "text": "ELIGIBILITY * Non-small cell lung cancer Clinical Stage 1A (T1N0M0 a tumor that is 3 cm or less in greatest dimension, surrounded by lung or visceral pleura, and without bronchoscopic evidence of invasion more proximal than the lobar bronchus (i.e., not in the main bronchus)\\* or 1B (T2N0M0 a tumor with any of the following features of size or extent: More than 3 cm in greatest dimension."
      }
    },
    {
      "id": "pubmed:32450775:1",
      "score": 0.5490708947181702,
      "metadata": {
        "id": "pubmed:32450775:1",
        "doc_id": "32450775",
        "source": "pubmed",
        "title": "Estimation of causal effects of multiple treatments in observational studies with a binary outcome.",
        "study_type": "Journal Article, Research Support, N.I.H., Extramural, Research Support, Non-U.S. Gov't",
        "year": "2020",
        "url": "https://pubmed.ncbi.nlm.nih.gov/32450775/",
        "text": "A case study examining the effects of three surgical approaches for non-small cell lung cancer demonstrates the methods."
      }
    },
    {
      "id": "pubmed:15110450:0",
      "score": 0.5490273237228394,
      "metadata": {
        "id": "pubmed:15110450:0",
        "doc_id": "15110450",
        "source": "pubmed",
        "title": "Radiation treatment of lung cancer--patterns of practice in Canada.",
        "study_type": "Comparative Study, Journal Article, Research Support, Non-U.S. Gov't",
        "year": "2004",
        "url": "https://pubmed.ncbi.nlm.nih.gov/15110450/",
        "text": "A questionnaire detailing different aspects of radiation treatment of lung cancer was mailed to all radiation oncologists treating lung cancer in Canada."
      }
    },
    {
      "id": "pubmed:33046839:1",
      "score": 0.5485356450080872,
      "metadata": {
        "id": "pubmed:33046839:1",
        "doc_id": "33046839",
        "source": "pubmed",
        "title": "Lung cancer LDCT screening and mortality reduction - evidence, pitfalls and future perspectives.",
        "study_type": "Journal Article, Review",
        "year": "2021",
        "url": "https://pubmed.ncbi.nlm.nih.gov/33046839/",
        "text": "Two large randomized controlled trials of low-dose CT (LDCT)-based lung cancer screening in high-risk populations - the US National Lung Screening Trial (NLST) and NELSON - have provided evidence of a statistically significant mortality reduction in patients."
      }
    },
    {
      "id": "pubmed:38799792:2",
      "score": 0.5484728217124939,
      "metadata": {
        "id": "pubmed:38799792:2",
        "doc_id": "38799792",
        "source": "pubmed",
        "title": "Lung cancer in the emergency department.",
        "study_type": "Journal Article, Review",
        "year": "2023",
        "url": "https://pubmed.ncbi.nlm.nih.gov/38799792/",
        "text": "The purpose of this review is to identify the many ways that emergency providers may intersect with the disease spectrum of lung cancer and provide an updated array of knowledge regarding detection, management, complications, and interdisciplinary care."
      }
    }
  ],
  "grouped_hits": [
    {
      "source": "pubmed",
      "doc_id": "27574741",
      "title": "Lung cancer: current therapies and new targeted treatments.",
      "study_type": "Journal Article, Review",
      "year": "2017",
      "url": "https://pubmed.ncbi.nlm.nih.gov/27574741/",
      "semantic_score": 0.6861160397529602,
      "matched_sentences": [
        "We discuss prevention and early detection of lung cancer with an emphasis on lung cancer screening."
      ]
    },
    {
      "source": "clinicaltrials",
      "doc_id": "NCT02916745",
      "title": "Feasibility Study of Using Navigational Bronchoscopy to Perform PDT-Photofrin® in Unresectable Peripheral Lung Cancer",
      "study_type": "INTERVENTIONAL",
      "year": "2020",
      "url": "https://clinicaltrials.gov/study/NCT02916745",
      "semantic_score": 0.6776835322380066,
      "matched_sentences": [
        "Lung cancer accounts for almost one-third of cancer deaths."
      ]
    },
    {
      "source": "pubmed",
      "doc_id": "30572031",
      "title": "Best Practices Recommendations for Diagnostic Immunohistochemistry in Lung Cancer.",
      "study_type": "Journal Article, Research Support, Non-U.S. Gov't",
      "year": "2019",
      "url": "https://pubmed.ncbi.nlm.nih.gov/30572031/",
      "semantic_score": 0.6726204752922058,
      "matched_sentences": [
        "After discussions in several International Association for the Study of Lung Cancer Pathology Committee meetings, the issues and caveats were summarized in terms of 11 key questions covering common and important diagnostic situations in a daily clinical practice with some relevant challenging queries."
      ]
    },
    {
      "source": "pubmed",
      "doc_id": "33972746",
      "title": "COVID-19 and the multidisciplinary care of patients with lung cancer: an evidence-based review and commentary.",
      "study_type": "Journal Article, Research Support, Non-U.S. Gov't, Review",
      "year": "2021",
      "url": "https://pubmed.ncbi.nlm.nih.gov/33972746/",
      "semantic_score": 0.6709849834442139,
      "matched_sentences": [
        "Review of current evidence and commentary included awareness and help-seeking; lung cancer screening; primary care assessment and referral; diagnosis and treatment in secondary care, including oncology and surgery; patient experience and palliative care.",
        "We searched for COVID-19 and lung cancer publications and brought together a multidisciplinary group of stakeholders to review and comment on the evidence and challenges.",
        "There is a lack of published COVID-19 and lung cancer evidence-based reviews, including for the whole patient pathway."
      ]
    },
    {
      "source": "pubmed",
      "doc_id": "39118957",
      "title": "Review on endobronchial therapies-current status and future.",
      "study_type": "Journal Article, Review",
      "year": "2024",
      "url": "https://pubmed.ncbi.nlm.nih.gov/39118957/",
      "semantic_score": 0.6483585834503174,
      "matched_sentences": [
        "Lung cancer screening has led to the discovery of more pre-malignant or early-stage lung cancers, and the focus has shifted from treatment to prevention."
      ]
    },
    {
      "source": "pubmed",
      "doc_id": "35369606",
      "title": "Trends of Molecular Testing for Lung Cancer at the King Faisal Hospital, Kigali: Therapeutic and Survival Implications.",
      "study_type": "Journal Article",
      "year": "2022",
      "url": "https://pubmed.ncbi.nlm.nih.gov/35369606/",
      "semantic_score": 0.6465158462524414,
      "matched_sentences": [
        "This study describes the experience in lung cancer diagnosis, molecular and biomarker testing, and treatment for advanced cases in a single institution in East Africa, between the years 2019 and 2021.",
        "This was a retrospective observational study evaluating patients with metastatic (stage IV) lung cancer.",
        "Little is known on the data around lung cancer and its treatment outcomes in Sub-Saharan Africa."
      ]
    },
    {
      "source": "clinicaltrials",
      "doc_id": "NCT03576937",
      "title": "Achieving Value in Cancer Diagnostics: Blood Versus Tissue Molecular Profiling - a Prospective Canadian Study",
      "study_type": "OBSERVATIONAL",
      "year": "2023",
      "url": "https://clinicaltrials.gov/study/NCT03576937",
      "semantic_score": 0.6338520050048828,
      "matched_sentences": [
        "However, obtaining sufficient tumour tissue to test for these molecular alterations, as well as those with emerging targeted therapies, is challenging in lung cancer."
      ]
    },
    {
      "source": "pubmed",
      "doc_id": "29355391",
      "title": "Updated Molecular Testing Guideline for the Selection of Lung Cancer Patients for Treatment With Targeted Tyrosine Kinase Inhibitors: Guideline From the College of American Pathologists, the International Association for the Study of Lung Cancer, and the Association for Molecular Pathology.",
      "study_type": "Journal Article, Practice Guideline",
      "year": "2018",
      "url": "https://pubmed.ncbi.nlm.nih.gov/29355391/",
      "semantic_score": 0.6326690912246704,
      "matched_sentences": [
        "- The College of American Pathologists, the International Association for the Study of Lung Cancer, and the Association for Molecular Pathology convened an expert panel to develop an evidence-based guideline to help define the key questions and literature search terms, review abstracts and full articles, and draft recommendations.",
        "- In 2013, an evidence-based guideline was published by the College of American Pathologists, the International Association for the Study of Lung Cancer, and the Association for Molecular Pathology to set standards for the molecular analysis of lung cancers to guide treatment decisions with targeted inhibitors."
      ]
    },
    {
      "source": "pubmed",
      "doc_id": "30211037",
      "title": "The 8",
      "study_type": "Journal Article, Review",
      "year": "2018",
      "url": "https://pubmed.ncbi.nlm.nih.gov/30211037/",
      "semantic_score": 0.6316414475440979,
      "matched_sentences": [
        "Guidelines are constantly being reviewed as more data becomes available to provide the most accurate prognostic markers, hence aiding in the clinical detection and staging of lung cancer.",
        "Lung cancer is the leading cause of cancer death in both men and women."
      ]
    },
    {
      "source": "pubmed",
      "doc_id": "29700105",
      "title": "Lung cancer staging: a concise update.",
      "study_type": "Journal Article, Review",
      "year": "2018",
      "url": "https://pubmed.ncbi.nlm.nih.gov/29700105/",
      "semantic_score": 0.6301765441894531,
      "matched_sentences": [
        "Diagnosis and clinical staging of lung cancer are fundamental to planning therapy."
      ]
    },
    {
      "source": "pubmed",
      "doc_id": "41307293",
      "title": "Long-term hormone therapy for perimenopausal and postmenopausal women.",
      "study_type": "Journal Article, Systematic Review",
      "year": "2025",
      "url": "https://pubmed.ncbi.nlm.nih.gov/41307293/",
      "semantic_score": 0.627196729183197,
      "matched_sentences": [
        "It may make little to no difference to the risk of lung cancer (RR 1.04, 95% CI 0.73 to 1.48; low-certainty evidence)."
      ]
    },
    {
      "source": "pubmed",
      "doc_id": "38641511",
      "title": "Development of new techniques and clinical applications of liquid biopsy in lung cancer management.",
      "study_type": "Journal Article, Review, Research Support, Non-U.S. Gov't",
      "year": "2024",
      "url": "https://pubmed.ncbi.nlm.nih.gov/38641511/",
      "semantic_score": 0.6263546347618103,
      "matched_sentences": [
        "Lung cancer is an exceedingly malignant tumor reported as having the highest morbidity and mortality of any cancer worldwide, thus posing a great threat to global health.",
        "Additionally, it will summarize the latest applications of liquid biopsy for the early detection, diagnosis, treatment, and prognosis of lung cancer."
      ]
    },
    {
      "source": "pubmed",
      "doc_id": "34753715",
      "title": "Advances in systemic therapy for non-small cell lung cancer.",
      "study_type": "Journal Article, Review",
      "year": "2021",
      "url": "https://pubmed.ncbi.nlm.nih.gov/34753715/",
      "semantic_score": 0.6263513565063477,
      "matched_sentences": [
        "Lung cancer remains a leading cause of cancer related mortality worldwide."
      ]
    },
    {
      "source": "openalex",
      "doc_id": "https://openalex.org/W2106787323",
      "title": "Global cancer statistics",
      "study_type": "article",
      "year": "2011",
      "url": "https://doi.org/10.3322/caac.20107",
      "semantic_score": 0.6259598135948181,
      "matched_sentences": [
        "Lung cancer is the leading cancer site in males, comprising 17% of the total new cancer cases and 23% of the total cancer deaths."
      ]
    },
    {
      "source": "pubmed",
      "doc_id": "24067269",
      "title": "Lung cancer: needs assessment, treatment and therapies.",
      "study_type": "Journal Article, Review",
      "year": "2013",
      "url": "https://pubmed.ncbi.nlm.nih.gov/24067269/",
      "semantic_score": 0.62464439868927,
      "matched_sentences": [
        "It is not within the scope of this article to discuss each type and aspect of lung cancer in detail and further reading is encouraged.",
        "The latest figures for the UK show that there are approximately 39000 cases each year and that lung cancer accounts for about 22% of all cancer deaths (Cancer Research UK, 2013a)."
      ]
    },
    {
      "source": "pubmed",
      "doc_id": "34847189",
      "title": "Countering the advert effects of lung cancer on the anticancer potential of dendritic cell populations reinstates sensitivity to anti-PD-1 therapy.",
      "study_type": "Journal Article, Research Support, Non-U.S. Gov't",
      "year": "2021",
      "url": "https://pubmed.ncbi.nlm.nih.gov/34847189/",
      "semantic_score": 0.622816801071167,
      "matched_sentences": [
        "Lung cancer is the leading cause of cancer-related deaths."
      ]
    },
    {
      "source": "pubmed",
      "doc_id": "40480014",
      "title": "AGREE-II appraisal of lung cancer management clinical practice guidelines by the OPTIMA consortium.",
      "study_type": "Journal Article",
      "year": "2025",
      "url": "https://pubmed.ncbi.nlm.nih.gov/40480014/",
      "semantic_score": 0.6220012903213501,
      "matched_sentences": [
        "We identified and critically appraised 21 European lung cancer guidelines published between 2009 and 2025."
      ]
    },
    {
      "source": "pubmed",
      "doc_id": "35323350",
      "title": "Non-Small-Cell Lung Cancer in 2022: A Review for General Practitioners in Oncology.",
      "study_type": "Journal Article, Review",
      "year": "2022",
      "url": "https://pubmed.ncbi.nlm.nih.gov/35323350/",
      "semantic_score": 0.6165987253189087,
      "matched_sentences": [
        "The focus of this review is to highlight recent data in screening for lung cancer, management of patients with early and locally-advanced non-small cell lung cancer, as well as management of patients with metastatic disease.",
        "Lung cancer is the leading cause of cancer death in Canada and a significant cause of morbidity for patients and their loved ones."
      ]
    },
    {
      "source": "clinicaltrials",
      "doc_id": "NCT04035486",
      "title": "A Study of Osimertinib With or Without Chemotherapy as 1st Line Treatment in Patients With Mutated Epidermal Growth Factor Receptor Non-Small Cell Lung Cancer (FLAURA2)",
      "study_type": "INTERVENTIONAL",
      "year": "2025",
      "url": "https://clinicaltrials.gov/study/NCT04035486",
      "semantic_score": 0.6159894466400146,
      "matched_sentences": [
        "Some lung cancers are due to mutations in the Deoxyribonucleic acid (DNA) which, if known, can help physicians decide the best treatment for their patients."
      ]
    },
    {
      "source": "pubmed",
      "doc_id": "15110450",
      "title": "Radiation treatment of lung cancer--patterns of practice in Canada.",
      "study_type": "Comparative Study, Journal Article, Research Support, Non-U.S. Gov't",
      "year": "2004",
      "url": "https://pubmed.ncbi.nlm.nih.gov/15110450/",
      "semantic_score": 0.6140954494476318,
      "matched_sentences": [
        "Canadian practice in the treatment of lung cancers shows some variations although it is consistent with the trends in the literature.",
        "A questionnaire detailing different aspects of radiation treatment of lung cancer was mailed to all radiation oncologists treating lung cancer in Canada."
      ]
    },
    {
      "source": "pubmed",
      "doc_id": "40133478",
      "title": "Update 2025: Management of Non‑Small-Cell Lung Cancer.",
      "study_type": "Journal Article, Review",
      "year": "2025",
      "url": "https://pubmed.ncbi.nlm.nih.gov/40133478/",
      "semantic_score": 0.6130865216255188,
      "matched_sentences": [
        "Lung cancer remains the leading cause of cancer-related mortality worldwide."
      ]
    },
    {
      "source": "pubmed",
      "doc_id": "40871018",
      "title": "Inhalable Nanomaterial Discoveries for Lung Cancer Therapy: A Review.",
      "study_type": "Journal Article, Review",
      "year": "2025",
      "url": "https://pubmed.ncbi.nlm.nih.gov/40871018/",
      "semantic_score": 0.6128694415092468,
      "matched_sentences": [
        "Lung cancer remains one of the most common and deadliest forms of cancer worldwide despite notable advancements in its management."
      ]
    },
    {
      "source": "pubmed",
      "doc_id": "41526992",
      "title": "LUNG CARCINOIDS (Lung Neuroendocrine Tumors).",
      "study_type": "Journal Article",
      "year": "2026",
      "url": "https://pubmed.ncbi.nlm.nih.gov/41526992/",
      "semantic_score": 0.6127306222915649,
      "matched_sentences": [
        "This narrative review written by experts aims to provide a comprehensive synthesis of current knowledge and guidelines on lung carcinoids, emphasizing the multidimensional approach required for effective diagnosis and management."
      ]
    },
    {
      "source": "pubmed",
      "doc_id": "33175991",
      "title": "Update 2020: Management of Non-Small Cell Lung Cancer.",
      "study_type": "Journal Article, Review",
      "year": "2020",
      "url": "https://pubmed.ncbi.nlm.nih.gov/33175991/",
      "semantic_score": 0.612597644329071,
      "matched_sentences": [
        "This review will address updates in lung cancer screening, liquid biopsy, and immunotherapy in the front-line setting."
      ]
    },
    {
      "source": "pubmed",
      "doc_id": "39337530",
      "title": "Emerging Targets in Non-Small Cell Lung Cancer.",
      "study_type": "Journal Article, Review",
      "year": "2024",
      "url": "https://pubmed.ncbi.nlm.nih.gov/39337530/",
      "semantic_score": 0.6121392250061035,
      "matched_sentences": [
        "Lung cancer is responsible for a high burden of disease globally."
      ]
    },
    {
      "source": "pubmed",
      "doc_id": "41024606",
      "title": "American Association for Bronchology and Interventional Pulmonology (AABIP) Evidence-Based Guidelines on Bronchoscopic Diagnosis and Staging of Lung Cancer.",
      "study_type": "Journal Article, Practice Guideline",
      "year": "2025",
      "url": "https://pubmed.ncbi.nlm.nih.gov/41024606/",
      "semantic_score": 0.6097329258918762,
      "matched_sentences": [
        "Lung cancer remains a predominant cause of cancer-related deaths worldwide, and there are notable geographic and institutional differences in both diagnostic and staging approaches.",
        "These guidelines aim to standardize and streamline recommendations for the bronchoscopic diagnosis and staging of lung cancer."
      ]
    },
    {
      "source": "pubmed",
      "doc_id": "29352525",
      "title": "An MRM-Based Cytokeratin Marker Assay as a Tool for Cancer Studies: Application to Lung Cancer Pleural Effusions.",
      "study_type": "Journal Article, Research Support, Non-U.S. Gov't",
      "year": "2018",
      "url": "https://pubmed.ncbi.nlm.nih.gov/29352525/",
      "semantic_score": 0.6045322418212891,
      "matched_sentences": [
        "An MRM-based CK assay for carcinoma studies can differentiate between the three lung cancer histological types using less-invasive PE sampling providing potential therapy-guiding information on patients that are inoperable."
      ]
    },
    {
      "source": "pubmed",
      "doc_id": "36290875",
      "title": "Access to Cancer Drugs in Canada.",
      "study_type": "Editorial",
      "year": "2022",
      "url": "https://pubmed.ncbi.nlm.nih.gov/36290875/",
      "semantic_score": 0.6028514504432678,
      "matched_sentences": [
        "Lung cancer, because of the multiple subtypes now identifiable and because of the myriad of new and effective therapies, provides fertile ground to highlight issues related to oncology drug access in Canada [...]."
      ]
    },
    {
      "source": "pubmed",
      "doc_id": "19445746",
      "title": "Lung cancer.",
      "study_type": "Journal Article, Systematic Review",
      "year": "2009",
      "url": "https://pubmed.ncbi.nlm.nih.gov/19445746/",
      "semantic_score": 0.6016722321510315,
      "matched_sentences": [
        "What are the effects of treatments for small cell lung cancer?",
        "Lung cancer is the leading cause of cancer deaths in both men and women, with 80-90% of cases caused by smoking."
      ]
    },
    {
      "source": "pubmed",
      "doc_id": "21406127",
      "title": "Lung cancer.",
      "study_type": "Journal Article, Systematic Review",
      "year": "2010",
      "url": "https://pubmed.ncbi.nlm.nih.gov/21406127/",
      "semantic_score": 0.6016722321510315,
      "matched_sentences": [
        "What are the effects of treatments for small cell lung cancer?",
        "Lung cancer is the leading cause of cancer deaths in both men and women, with 80% to 90% of cases caused by smoking."
      ]
    },
    {
      "source": "pubmed",
      "doc_id": "26620497",
      "title": "Management of advanced non-small cell lung cancers with known mutations or rearrangements: latest evidence and treatment approaches.",
      "study_type": "Journal Article, Research Support, N.I.H., Extramural, Research Support, Non-U.S. Gov't, Review",
      "year": "2016",
      "url": "https://pubmed.ncbi.nlm.nih.gov/26620497/",
      "semantic_score": 0.5986562967300415,
      "matched_sentences": [
        "Precision oncology is now the evidence-based standard of care for the management of many advanced non-small cell lung cancers (NSCLCs)."
      ]
    },
    {
      "source": "pubmed",
      "doc_id": "38031889",
      "title": "What's new in thoracic oncology.",
      "study_type": "Journal Article, Review",
      "year": "2024",
      "url": "https://pubmed.ncbi.nlm.nih.gov/38031889/",
      "semantic_score": 0.5945765972137451,
      "matched_sentences": [
        "In this review, we will discuss new diagnostic techniques for lung cancer, innovations in surgery, and major updates on latest treatment options including immunotherapy."
      ]
    },
    {
      "source": "pubmed",
      "doc_id": "35732383",
      "title": "Personalised Lung Cancer Screening (PLuS) study to assess the importance of coexisting chronic conditions to clinical practice and policy: protocol for a multicentre observational study.",
      "study_type": "Journal Article, Research Support, Non-U.S. Gov't, Research Support, N.I.H., Extramural",
      "year": "2022",
      "url": "https://pubmed.ncbi.nlm.nih.gov/35732383/",
      "semantic_score": 0.5933829545974731,
      "matched_sentences": [
        "The Personalised Lung Cancer Screening (PLuS) study will help close this knowledge gap by leveraging real-world data to fully characterise LCS recipients."
      ]
    },
    {
      "source": "pubmed",
      "doc_id": "39236577",
      "title": "New diagnostic and nonsurgical local treatment modalities for early stage lung cancer.",
      "study_type": "Journal Article, Review",
      "year": "2024",
      "url": "https://pubmed.ncbi.nlm.nih.gov/39236577/",
      "semantic_score": 0.5902523398399353,
      "matched_sentences": [
        "This paper highlights developments in diagnostic and nonsurgical local treatment modalities that have changed the management of early-stage lung cancer."
      ]
    },
    {
      "source": "pubmed",
      "doc_id": "38878052",
      "title": "The 2023 American Association for Thoracic Surgery (AATS) Expert Consensus Document: Management of subsolid lung nodules.",
      "study_type": "Journal Article, Practice Guideline, Review, Consensus Statement",
      "year": "2024",
      "url": "https://pubmed.ncbi.nlm.nih.gov/38878052/",
      "semantic_score": 0.5892987847328186,
      "matched_sentences": [
        "Lung cancers that present as radiographic subsolid nodules represent a subtype with distinct biological behavior and outcomes."
      ]
    },
    {
      "source": "clinicaltrials",
      "doc_id": "NCT01351116",
      "title": "A Trial to Evaluate the Improvement in Lung Cancer Patients Receiving Radiation With or Without Brachytherapy",
      "study_type": "INTERVENTIONAL",
      "year": "2017",
      "url": "https://clinicaltrials.gov/study/NCT01351116",
      "semantic_score": 0.5888932943344116,
      "matched_sentences": [
        "Benefit will be assessed by measuring the proportion of patients who achieve symptomatic improvement in lung cancer symptoms."
      ]
    },
    {
      "source": "pubmed",
      "doc_id": "34862216",
      "title": "Lung cancer for the non-respiratory physician.",
      "study_type": "Journal Article, Review",
      "year": "2021",
      "url": "https://pubmed.ncbi.nlm.nih.gov/34862216/",
      "semantic_score": 0.5862986445426941,
      "matched_sentences": [
        "We provide an overview of the core lung cancer diagnostic steps, recognition and management of acute presentations as well as the latest treatment options.",
        "The new National Optimal Lung Cancer Pathway describes 'diagnostic standards of care' in an effort to implement best practice, reduce variation and improve delays in diagnosis, staging and treatment of lung cancer."
      ]
    },
    {
      "source": "pubmed",
      "doc_id": "17620772",
      "title": "Lung cancer adjuvant therapy.",
      "study_type": "Journal Article, Review",
      "year": "2007",
      "url": "https://pubmed.ncbi.nlm.nih.gov/17620772/",
      "semantic_score": 0.583954930305481,
      "matched_sentences": [
        "Lung cancer is the most common cause of cancer-related mortality in North America with non-small cell lung cancer representing the majority of cases."
      ]
    },
    {
      "source": "pubmed",
      "doc_id": "38417091",
      "title": "Therapy for Stage IV Non-Small Cell Lung Cancer With Driver Alterations: ASCO Living Guideline, Version 2023.3.",
      "study_type": "Journal Article, Practice Guideline, Systematic Review",
      "year": "2024",
      "url": "https://pubmed.ncbi.nlm.nih.gov/38417091/",
      "semantic_score": 0.5808396339416504,
      "matched_sentences": [
        "To provide evidence-based recommendations for patients with stage IV non-small cell lung cancer with driver alterations."
      ]
    },
    {
      "source": "pubmed",
      "doc_id": "41632926",
      "title": "Therapy for Stage IV Non-Small Cell Lung Cancer With Driver Alterations: ASCO Living Guideline, 2026.3.0.",
      "study_type": "Letter",
      "year": "2026",
      "url": "https://pubmed.ncbi.nlm.nih.gov/41632926/",
      "semantic_score": 0.5808396339416504,
      "matched_sentences": [
        "To provide evidence-based recommendations for patients with stage IV non-small cell lung cancer with driver alterations."
      ]
    },
    {
      "source": "pubmed",
      "doc_id": "27343441",
      "title": "Comprehensive Clinical Staging for Resectable Lung Cancer: Clinicopathological Correlations and the Role of Brain MRI.",
      "study_type": "Journal Article",
      "year": "2016",
      "url": "https://pubmed.ncbi.nlm.nih.gov/27343441/",
      "semantic_score": 0.5793554186820984,
      "matched_sentences": [
        "Of 315 patients with primary lung cancer, 55.6% were female and the mean age was 70 ± 9.6 years."
      ]
    },
    {
      "source": "pubmed",
      "doc_id": "36806787",
      "title": "Rare molecular subtypes of lung cancer.",
      "study_type": "Journal Article, Review, Research Support, N.I.H., Extramural, Research Support, Non-U.S. Gov't",
      "year": "2023",
      "url": "https://pubmed.ncbi.nlm.nih.gov/36806787/",
      "semantic_score": 0.5786510705947876,
      "matched_sentences": [
        "Oncogenes that occur in ≤5% of non-small-cell lung cancers have been defined as 'rare'; nonetheless, this frequency can correspond to a substantial number of patients diagnosed annually.",
        "Over the past 5 years, a surge in the identification of rare-oncogene-driven lung cancers has challenged the boundaries of traditional clinical grade diagnostic assays and profiling algorithms."
      ]
    },
    {
      "source": "pubmed",
      "doc_id": "26297204",
      "title": "Lung cancer: Biology and treatment options.",
      "study_type": "Journal Article, Research Support, N.I.H., Extramural, Research Support, Non-U.S. Gov't, Review",
      "year": "2015",
      "url": "https://pubmed.ncbi.nlm.nih.gov/26297204/",
      "semantic_score": 0.5749998092651367,
      "matched_sentences": [
        "Despite the improvements in diagnosis and therapy made during the past 25 years, the prognosis for patients with lung cancer is still unsatisfactory."
      ]
    },
    {
      "source": "pubmed",
      "doc_id": "41877745",
      "title": "The global cancer crisis: a review of growing burden, deepening inequality and initiatives for prevention and early detection.",
      "study_type": "Journal Article, Review",
      "year": "2026",
      "url": "https://pubmed.ncbi.nlm.nih.gov/41877745/",
      "semantic_score": 0.5696343779563904,
      "matched_sentences": [
        "Lung cancer leads the global toll, representing 12% of all cases but 19% of deaths, followed by breast cancer (12% of cases) and colorectal cancer (9.6%)."
      ]
    },
    {
      "source": "pubmed",
      "doc_id": "41632927",
      "title": "Therapy for Stage IV Non-Small Cell Lung Cancer Without Driver Alterations: ASCO Living Guideline, 2026.3.0.",
      "study_type": "Journal Article",
      "year": "2026",
      "url": "https://pubmed.ncbi.nlm.nih.gov/41632927/",
      "semantic_score": 0.5691902041435242,
      "matched_sentences": [
        "To provide evidence-based recommendations for patients with stage IV non-small cell lung cancer (NSCLC) without driver alterations."
      ]
    },
    {
      "source": "pubmed",
      "doc_id": "38417098",
      "title": "Therapy for Stage IV Non-Small Cell Lung Cancer Without Driver Alterations: ASCO Living Guideline, Version 2023.3.",
      "study_type": "Journal Article, Practice Guideline, Systematic Review",
      "year": "2024",
      "url": "https://pubmed.ncbi.nlm.nih.gov/38417098/",
      "semantic_score": 0.5691902041435242,
      "matched_sentences": [
        "To provide evidence-based recommendations for patients with stage IV non-small cell lung cancer (NSCLC) without driver alterations."
      ]
    },
    {
      "source": "clinicaltrials",
      "doc_id": "NCT04048954",
      "title": "Use of a Smartphone Application on the Detection of Complications Related to Smoking",
      "study_type": "OBSERVATIONAL",
      "year": "2020",
      "url": "https://clinicaltrials.gov/study/NCT04048954",
      "semantic_score": 0.5683777332305908,
      "matched_sentences": [
        "An English study showed an increase in the number of operable stage cancers of 3% among smokers by calling them on a trailing cough by a simple poster campaign (\"You smoke, you cough for more than 3 weeks, consult\")."
      ]
    },
    {
      "source": "pubmed",
      "doc_id": "34385702",
      "title": "Toward personalized treatment approaches for non-small-cell lung cancer.",
      "study_type": "Journal Article, Review",
      "year": "2021",
      "url": "https://pubmed.ncbi.nlm.nih.gov/34385702/",
      "semantic_score": 0.5674136877059937,
      "matched_sentences": [
        "Worldwide, lung cancer is the most common cause of cancer-related deaths."
      ]
    },
    {
      "source": "pubmed",
      "doc_id": "31049758",
      "title": "The Japanese Lung Cancer Society Guideline for non-small cell lung cancer, stage IV.",
      "study_type": "Journal Article, Practice Guideline",
      "year": "2019",
      "url": "https://pubmed.ncbi.nlm.nih.gov/31049758/",
      "semantic_score": 0.5655086040496826,
      "matched_sentences": [
        "Here, we report an English version of the Japan Lung Cancer Society Guidelines 2018 for NSCLC, stages IV."
      ]
    },
    {
      "source": "pubmed",
      "doc_id": "40334018",
      "title": "Immunotherapy for resectable lung cancer.",
      "study_type": "Journal Article, Review",
      "year": "2025",
      "url": "https://pubmed.ncbi.nlm.nih.gov/40334018/",
      "semantic_score": 0.5631258487701416,
      "matched_sentences": [
        "This comprehensive analysis amalgamates current evidence with future directions, providing a roadmap for clinicians, researchers, and stakeholders to navigate the dynamic realm of immunotherapy for surgically resectable lung cancer.",
        "Lung cancer remains a significant global health challenge, demanding innovative treatment strategies."
      ]
    },
    {
      "source": "pubmed",
      "doc_id": "36975758",
      "title": "Exploring state-of-the-art advances in targeted nanomedicines for managing acute and chronic inflammatory lung diseases.",
      "study_type": "Journal Article, Review",
      "year": "2022",
      "url": "https://pubmed.ncbi.nlm.nih.gov/36975758/",
      "semantic_score": 0.5621503591537476,
      "matched_sentences": [
        "Diagnosis and treatment of lung diseases pose serious challenges."
      ]
    },
    {
      "source": "clinicaltrials",
      "doc_id": "NCT04863924",
      "title": "Accelerating Lung Cancer Diagnosis Through Liquid Biopsy",
      "study_type": "OBSERVATIONAL",
      "year": "2025",
      "url": "https://clinicaltrials.gov/study/NCT04863924",
      "semantic_score": 0.5618106126785278,
      "matched_sentences": [
        "This study will assess the utility of liquid biopsy to accelerate the time to treatment for patients with newly diagnosed advanced non-small cell lung cancer, compared to the conventional diagnostic pathway of molecular testing of tumour tissue after imaging and biopsy."
      ]
    },
    {
      "source": "pubmed",
      "doc_id": "34879471",
      "title": "Anti PD-L1 antibody: is there a histologic-oriented efficacy? Focus on atezolizumab in squamous cell non-small cell lung cancer.",
      "study_type": "Journal Article, Review",
      "year": "2021",
      "url": "https://pubmed.ncbi.nlm.nih.gov/34879471/",
      "semantic_score": 0.5597547292709351,
      "matched_sentences": [
        "We searched for published clinical trials in Pubmed database, using the terms \"atezolizumab\", \"squamous cell lung cancer\", \"NSCLC\" and \"non-small cell lung cancer\"."
      ]
    },
    {
      "source": "openalex",
      "doc_id": "https://openalex.org/W2608738563",
      "title": "Phylogenetic ctDNA analysis depicts early-stage lung cancer evolution",
      "study_type": "article",
      "year": "2017",
      "url": "https://doi.org/10.1038/nature22364",
      "semantic_score": 0.5576596856117249,
      "matched_sentences": [
        "Phylogenetic ctDNA analysis depicts early-stage lung cancer evolution"
      ]
    },
    {
      "source": "pubmed",
      "doc_id": "34246791",
      "title": "Liquid Biopsy for Advanced NSCLC: A Consensus Statement From the International Association for the Study of Lung Cancer.",
      "study_type": "Journal Article, Review, Consensus Statement",
      "year": "2021",
      "url": "https://pubmed.ncbi.nlm.nih.gov/34246791/",
      "semantic_score": 0.55743807554245,
      "matched_sentences": [
        "Since the publication of the first International Association for the Study of Lung Cancer (IASLC) liquid biopsy statement in 2018, several additional advances have been made in this field, leading to changes in the therapeutic decision-making algorithm for advanced NSCLC and prompting this 2021 update."
      ]
    },
    {
      "source": "pubmed",
      "doc_id": "29364287",
      "title": "The biology and management of non-small cell lung cancer.",
      "study_type": "Journal Article, Research Support, Non-U.S. Gov't, Review",
      "year": "2018",
      "url": "https://pubmed.ncbi.nlm.nih.gov/29364287/",
      "semantic_score": 0.554533839225769,
      "matched_sentences": [
        "Important advancements in the treatment of non-small cell lung cancer (NSCLC) have been achieved over the past two decades, increasing our understanding of the disease biology and mechanisms of tumour progression, and advancing early detection and multimodal care."
      ]
    },
    {
      "source": "clinicaltrials",
      "doc_id": "NCT06105021",
      "title": "Phase I Study of Autologous CD8+ and CD4+ Engineered T Cell Receptor T Cells in Subjects With Advanced or Metastatic Solid Tumor",
      "study_type": "INTERVENTIONAL",
      "year": "2025",
      "url": "https://clinicaltrials.gov/study/NCT06105021",
      "semantic_score": 0.5543209910392761,
      "matched_sentences": [
        "The doctors there will regularly check the size of the cancer and the patient's health."
      ]
    },
    {
      "source": "pubmed",
      "doc_id": "32005431",
      "title": "Targeted Therapy and Checkpoint Immunotherapy in Lung Cancer.",
      "study_type": "Journal Article, Review",
      "year": "2020",
      "url": "https://pubmed.ncbi.nlm.nih.gov/32005431/",
      "semantic_score": 0.5533599853515625,
      "matched_sentences": [
        "Comprehensive molecular characterization of lung cancer has expanded our understanding of the cellular origins and molecular pathways affected in each of these subtypes."
      ]
    },
    {
      "source": "pubmed",
      "doc_id": "39064229",
      "title": "Advances in Non-Small Cell Lung Cancer: Current Insights and Future Directions.",
      "study_type": "Journal Article, Review",
      "year": "2024",
      "url": "https://pubmed.ncbi.nlm.nih.gov/39064229/",
      "semantic_score": 0.5523355603218079,
      "matched_sentences": [
        "The leading cause of cancer deaths worldwide is attributed to non-small cell lung cancer (NSCLC), necessitating a continual focus on improving the diagnosis and treatment of this disease."
      ]
    },
    {
      "source": "pubmed",
      "doc_id": "37909877",
      "title": "Screening for lung cancer: 2023 guideline update from the American Cancer Society.",
      "study_type": "Journal Article, Research Support, Non-U.S. Gov't, Practice Guideline",
      "year": "2024",
      "url": "https://pubmed.ncbi.nlm.nih.gov/37909877/",
      "semantic_score": 0.5518502593040466,
      "matched_sentences": [
        "If fully implemented, these recommendations have a high likelihood of significantly reducing death and suffering from lung cancer in the United States."
      ]
    },
    {
      "source": "clinicaltrials",
      "doc_id": "NCT00188617",
      "title": "Phase 2 Study Of Neoadjuvant Iressa Treatment In Stage 1 NSCLC",
      "study_type": "INTERVENTIONAL",
      "year": "2017",
      "url": "https://clinicaltrials.gov/study/NCT00188617",
      "semantic_score": 0.5495622158050537,
      "matched_sentences": [
        "ELIGIBILITY * Non-small cell lung cancer Clinical Stage 1A (T1N0M0 a tumor that is 3 cm or less in greatest dimension, surrounded by lung or visceral pleura, and without bronchoscopic evidence of invasion more proximal than the lobar bronchus (i.e., not in the main bronchus)\\* or 1B (T2N0M0 a tumor with any of the following features of size or extent: More than 3 cm in greatest dimension."
      ]
    },
    {
      "source": "pubmed",
      "doc_id": "32450775",
      "title": "Estimation of causal effects of multiple treatments in observational studies with a binary outcome.",
      "study_type": "Journal Article, Research Support, N.I.H., Extramural, Research Support, Non-U.S. Gov't",
      "year": "2020",
      "url": "https://pubmed.ncbi.nlm.nih.gov/32450775/",
      "semantic_score": 0.5490708947181702,
      "matched_sentences": [
        "A case study examining the effects of three surgical approaches for non-small cell lung cancer demonstrates the methods."
      ]
    },
    {
      "source": "pubmed",
      "doc_id": "33046839",
      "title": "Lung cancer LDCT screening and mortality reduction - evidence, pitfalls and future perspectives.",
      "study_type": "Journal Article, Review",
      "year": "2021",
      "url": "https://pubmed.ncbi.nlm.nih.gov/33046839/",
      "semantic_score": 0.5485356450080872,
      "matched_sentences": [
        "Two large randomized controlled trials of low-dose CT (LDCT)-based lung cancer screening in high-risk populations - the US National Lung Screening Trial (NLST) and NELSON - have provided evidence of a statistically significant mortality reduction in patients."
      ]
    },
    {
      "source": "pubmed",
      "doc_id": "38799792",
      "title": "Lung cancer in the emergency department.",
      "study_type": "Journal Article, Review",
      "year": "2023",
      "url": "https://pubmed.ncbi.nlm.nih.gov/38799792/",
      "semantic_score": 0.5484728217124939,
      "matched_sentences": [
        "The purpose of this review is to identify the many ways that emergency providers may intersect with the disease spectrum of lung cancer and provide an updated array of knowledge regarding detection, management, complications, and interdisciplinary care."
      ]
    }
  ]
}